blurhash_avif/__init__.py
blurhash_avif/blurhash_avif.py
blurhash_avif/py.typed
blurhash_avif-0.8.5.dist-info/METADATA
blurhash_avif-0.8.5.dist-info/WHEEL
blurhash_avif-0.8.5.dist-info/licenses/LICENSE
blurhash_avif-0.8.5.dist-info/RECORD
