Metadata-Version: 2.4
Name: blurhash-avif
Version: 0.8.5
Summary: A library to generate BlurHash and PNG data URLs for AVIF images
Project-URL: Homepage, https://github.com/ZuidVolt/blurhash-avif
Project-URL: Repository, https://github.com/ZuidVolt/blurhash-avif
Project-URL: Issue Tracker, https://github.com/ZuidVolt/blurhash-avif/issues
Project-URL: Changelog, https://github.com/ZuidVolt/blurhash-avif/releases
Project-URL: Documentation, https://github.com/ZuidVolt/blurhash-avif/blob/main/README.md
Author: ZuidVolt
License: Apache-2.0
License-File: LICENSE
Keywords: avif,blurhash,image,image-processing
Classifier: License :: OSI Approved :: Apache Software License
Classifier: Operating System :: OS Independent
Classifier: Programming Language :: Python :: 3
Requires-Python: >=3.9
Requires-Dist: blurhash
Requires-Dist: numpy
Requires-Dist: pillow
Requires-Dist: pillow-avif-plugin
